jaxlib/__init__.py
jaxlib/_ifrt_proxy.so
jaxlib/_jax.so
jaxlib/_pathways.so
jaxlib/_pretty_printer.so
jaxlib/_profile_data.so
jaxlib/_profiler.so
jaxlib/_sdy_mpmd.so
jaxlib/cpu_feature_guard.so
jaxlib/cpu_sparse.py
jaxlib/gpu_common_utils.py
jaxlib/gpu_linalg.py
jaxlib/gpu_prng.py
jaxlib/gpu_rnn.py
jaxlib/gpu_solver.py
jaxlib/gpu_sparse.py
jaxlib/gpu_triton.py
jaxlib/lapack.py
jaxlib/libjax_common.dylib
jaxlib/plugin_support.py
jaxlib/py.typed
jaxlib/utils.so
jaxlib/version.py
jaxlib/weakref_lru_cache.pyi
jaxlib/weakref_lru_cache.so
jaxlib/xla_client.py
jaxlib/cpu/_lapack.so
jaxlib/cpu/_sparse.so
jaxlib/include/xla/ffi/api/api.h
jaxlib/include/xla/ffi/api/c_api.h
jaxlib/include/xla/ffi/api/ffi.h
jaxlib/mlir/ir.py
jaxlib/mlir/passmanager.py
jaxlib/mlir/_mlir_libs/__init__.py
jaxlib/mlir/_mlir_libs/_chlo.so
jaxlib/mlir/_mlir_libs/_jax_mlir_ext.so
jaxlib/mlir/_mlir_libs/_mlir.so
jaxlib/mlir/_mlir_libs/_mlirDialectsGPU.so
jaxlib/mlir/_mlir_libs/_mlirDialectsLLVM.so
jaxlib/mlir/_mlir_libs/_mlirDialectsNVGPU.so
jaxlib/mlir/_mlir_libs/_mlirDialectsSparseTensor.so
jaxlib/mlir/_mlir_libs/_mlirGPUPasses.so
jaxlib/mlir/_mlir_libs/_mlirHlo.so
jaxlib/mlir/_mlir_libs/_mlirSparseTensorPasses.so
jaxlib/mlir/_mlir_libs/_mosaic_gpu_ext.so
jaxlib/mlir/_mlir_libs/_sdy.so
jaxlib/mlir/_mlir_libs/_sdyMpmd.so
jaxlib/mlir/_mlir_libs/_stablehlo.so
jaxlib/mlir/_mlir_libs/_tpu_ext.so
jaxlib/mlir/_mlir_libs/_triton_ext.pyi
jaxlib/mlir/_mlir_libs/_triton_ext.so
jaxlib/mlir/dialects/_arith_enum_gen.py
jaxlib/mlir/dialects/_arith_ops_gen.py
jaxlib/mlir/dialects/_builtin_ops_gen.py
jaxlib/mlir/dialects/_cf_ops_gen.py
jaxlib/mlir/dialects/_chlo_ops_gen.py
jaxlib/mlir/dialects/_func_ops_gen.py
jaxlib/mlir/dialects/_gpu_enum_gen.py
jaxlib/mlir/dialects/_gpu_ops_gen.py
jaxlib/mlir/dialects/_llvm_enum_gen.py
jaxlib/mlir/dialects/_llvm_ops_gen.py
jaxlib/mlir/dialects/_math_ops_gen.py
jaxlib/mlir/dialects/_memref_ops_gen.py
jaxlib/mlir/dialects/_mhlo_ops_gen.py
jaxlib/mlir/dialects/_mpmd_ops_gen.py
jaxlib-0.9.0.dist-info/licenses/LICENSE.txt
jaxlib-0.9.0.dist-info/METADATA
jaxlib-0.9.0.dist-info/WHEEL
jaxlib-0.9.0.dist-info/top_level.txt
jaxlib-0.9.0.dist-info/RECORD
